{
  "coinDenom": "stINJ",
  "minCoinDenom": "stinj",
  "imgSrc": "https://raw.githubusercontent.com/cosmos/chain-registry/master/stride/images/stinj.svg",
  "pngSrc": "https://raw.githubusercontent.com/cosmos/chain-registry/master/stride/images/stinj.png",
  "type": "IBC",
  "exponent": "18",
  "cosmosDenom": "ibc/4FCDD6D71CAB4F6BBEAB781D036977E1158075297671345055BC342D46819640",
  "description": "Staking derivative by Stride",
  "name": "Stride Staked Inj",
  "tokenRepresentation": "INJ",
  "channel": "channel-25",
  "isEnabled": true,
  "erc20Address": "0x786744d8B40ee154FA4a74153c4d33dF09aBf015",
  "ibc": {
    "sourceDenom": "stinj",
    "source": "Stride"
  },
  "hideFromTestnet": false,
  "coingeckoId": "",
  "category": "cosmos",
  "coinSourcePrefix": "stride"
}
